{
    "version": "4.55.0",
    "description": "The Confluent command-line interface (CLI)",
    "license": "https://github.com/confluentinc/cli/blob/main/LICENSE",
    "homepage": "https://docs.confluent.io/confluent-cli/current/overview.html",
    "architecture": {
        "64bit": {
            "url": "https://github.com/confluentinc/cli/releases/download/v4.55.0/confluent_4.55.0_windows_amd64.zip",
            "hash": "c0a8009f3d27eb7aaf37ba83c88d9b91a84ae8115d8c73e48e23cf770c31613f"
        }
    },
    "extract_dir": "confluent",
    "bin": "confluent.exe",
    "checkver": {
        "github": "https://github.com/confluentinc/cli"
    },
    "autoupdate": {
        "architecture": {
            "64bit": {
                "url": "https://github.com/confluentinc/cli/releases/download/v$version/confluent_$version_windows_amd64.zip"
            }
        },
        "hash": {
            "url": "$baseurl/confluent_checksums.txt"
        }
    }
}
