{
    "version": "29.30.0",
    "description": "A prompt theme engine for any shell",
    "homepage": "https://ohmyposh.dev",
    "license": "MIT",
    "notes": "Refer to 'https://ohmyposh.dev/docs/installation/prompt' for shell specific configurations.",
    "architecture": {
        "64bit": {
            "url": [
                "https://github.com/JanDeDobbeleer/oh-my-posh/releases/download/v29.30.0/themes.zip",
                "https://github.com/JanDeDobbeleer/oh-my-posh/releases/download/v29.30.0/posh-windows-amd64.exe#/oh-my-posh.exe"
            ],
            "hash": [
                "a7783b04b807ba7eb708dbd6eebd91c85b542153329d86e778d42e6c6dad22a8",
                "fd4924ca5eb6ef634e8755f5f8d89133254e197c29e0960395b864788b5131aa"
            ]
        },
        "arm64": {
            "url": [
                "https://github.com/JanDeDobbeleer/oh-my-posh/releases/download/v29.30.0/themes.zip",
                "https://github.com/JanDeDobbeleer/oh-my-posh/releases/download/v29.30.0/posh-windows-arm64.exe#/oh-my-posh.exe"
            ],
            "hash": [
                "a7783b04b807ba7eb708dbd6eebd91c85b542153329d86e778d42e6c6dad22a8",
                "217ed13d1fc539d026852da34b5fadac97626aebad9c34f7d2005e8ec0ffcad3"
            ]
        }
    },
    "extract_to": "themes",
    "env_set": {
        "POSH_THEMES_PATH": "$dir\\themes"
    },
    "bin": "oh-my-posh.exe",
    "checkver": {
        "github": "https://github.com/JanDeDobbeleer/oh-my-posh"
    },
    "autoupdate": {
        "architecture": {
            "64bit": {
                "url": [
                    "https://github.com/JanDeDobbeleer/oh-my-posh/releases/download/v$version/themes.zip",
                    "https://github.com/JanDeDobbeleer/oh-my-posh/releases/download/v$version/posh-windows-amd64.exe#/oh-my-posh.exe"
                ]
            },
            "arm64": {
                "url": [
                    "https://github.com/JanDeDobbeleer/oh-my-posh/releases/download/v$version/themes.zip",
                    "https://github.com/JanDeDobbeleer/oh-my-posh/releases/download/v$version/posh-windows-arm64.exe#/oh-my-posh.exe"
                ]
            }
        }
    }
}
